UNTDA/__init__.py
UNTDA/basicpersistencetools.py
UNTDA/color.py
UNTDA/examples.py
UNTDA/setup.py
UNTDA-0.3.0.1.dist-info/LICENSE
UNTDA-0.3.0.1.dist-info/METADATA
UNTDA-0.3.0.1.dist-info/WHEEL
UNTDA-0.3.0.1.dist-info/top_level.txt
UNTDA-0.3.0.1.dist-info/RECORD
