Metadata-Version: 2.1
Name: UNTDA
Version: 0.3.0.1
Summary: paquete de aprendizaje de TDA - UNAL Colombia
Home-page: https://github.com/izainea/UNATD
Author: Isaac Zainea
Author-email: isaaczainea@gmail.com
License: UNKNOWN
Keywords: testing,ATD,TDA
Platform: UNKNOWN
Classifier: Programming Language :: Python :: 3
Classifier: License :: OSI Approved :: MIT License
Classifier: Operating System :: OS Independent
